debugtwin_cli/__init__.py
debugtwin_cli/main.py
debugtwin_cli-1.0.6.dist-info/METADATA
debugtwin_cli-1.0.6.dist-info/WHEEL
debugtwin_cli-1.0.6.dist-info/entry_points.txt
debugtwin_cli-1.0.6.dist-info/top_level.txt
debugtwin_cli-1.0.6.dist-info/RECORD
