Metadata-Version: 2.4
Name: debugtwin-cli
Version: 1.0.6
Summary: DebugTwin Copilot CLI - AI-powered firmware debugging assistant
Author-email: Frozo <support@frozo.io>
License: MIT
Project-URL: Homepage, https://github.com/ashish-frozo/embedded-client
Project-URL: Documentation, https://embedded-frontend-production.up.railway.app
Project-URL: Repository, https://github.com/ashish-frozo/embedded-client
Keywords: firmware,debugging,embedded,ai,copilot,cli
Classifier: Development Status :: 4 - Beta
Classifier: Environment :: Console
Classifier: Intended Audience :: Developers
Classifier: License :: OSI Approved :: MIT License
Classifier: Operating System :: OS Independent
Classifier: Programming Language :: Python :: 3
Classifier: Programming Language :: Python :: 3.9
Classifier: Programming Language :: Python :: 3.10
Classifier: Programming Language :: Python :: 3.11
Classifier: Programming Language :: Python :: 3.12
Classifier: Topic :: Software Development :: Debuggers
Classifier: Topic :: Software Development :: Embedded Systems
Requires-Python: >=3.9
Requires-Dist: click>=8.0.0
Requires-Dist: aiohttp>=3.8.0
Requires-Dist: rich>=13.0.0
